Metadata-Version: 1.0
Name: MyNode
Version: 1.1
Summary: Simplificando el uso de titulos y haciendo un print como en javascript & node.js y tambien agregando la funcion loop para repetir un texto especifico una cantidad de veces especificas!
Home-page: UNKNOWN
Author: Andresdes266
Author-email: andresdes266@email.com
License: MIT
Platform: UNKNOWN
